clipboardhist/__init__.py
clipboardhist/clipboardhist.py
clipboardhist-1.0.5.dist-info/LICENSE
clipboardhist-1.0.5.dist-info/METADATA
clipboardhist-1.0.5.dist-info/WHEEL
clipboardhist-1.0.5.dist-info/top_level.txt
clipboardhist-1.0.5.dist-info/RECORD
